uv_up/__init__.py
uv_up/__main__.py
uv_up/cli.py
uv_up/manager.py
uv_up-0.1.0.dist-info/METADATA
uv_up-0.1.0.dist-info/WHEEL
uv_up-0.1.0.dist-info/entry_points.txt
uv_up-0.1.0.dist-info/top_level.txt
uv_up-0.1.0.dist-info/RECORD
