Metadata-Version: 2.1
Name: uv-up
Version: 0.1.0
Summary: Better tool to update all dependencies
Requires-Python: >=3.12
Requires-Dist: typer >=0.12.5
Requires-Dist: packaging >=24.1
Requires-Dist: tomlkit >=0.13.2
Requires-Dist: pip-api >=0.0.34
